setup.py
MediaManipulationDetector/FeaturesExtraction.py
MediaManipulationDetector/FeaturesReduction.py
MediaManipulationDetector/ManipulationDetector.py
MediaManipulationDetector/ModelCreation.py
MediaManipulationDetector/RadialProfile.py
MediaManipulationDetector/ResultsExporter.py
MediaManipulationDetector/__init__.py
Media_Manipulation_Detector.egg-info/PKG-INFO
Media_Manipulation_Detector.egg-info/SOURCES.txt
Media_Manipulation_Detector.egg-info/dependency_links.txt
Media_Manipulation_Detector.egg-info/top_level.txt