Metadata-Version: 1.0
Name: Media-Manipulation-Detector
Version: 0.0.2
Summary: Module created to detect manipulated media
Home-page: UNKNOWN
Author: David Maia
Author-email: UNKNOWN
License: UNKNOWN
Platform: UNKNOWN
